{
  "collectionName": "components_section_section_metadata",
  "info": {
    "displayName": "section_metadata"
  },
  "options": {},
  "attributes": {
    "name": {
      "type": "string",
      "required": true,
      "unique": false,
      "minLength": 5,
      "maxLength": 255
    },
    "section_id": {
      "type": "string",
      "required": true,
      "maxLength": 50,
      "minLength": 3,
      "unique": false
    },
    "background": {
      "type": "boolean",
      "default": false,
      "required": true
    }
  }
}
